liveline/__init__.py
liveline/context.py
liveline/engine.py
liveline/execution_data_store.py
liveline/data/__init__.py
liveline/data/data_provider.py
liveline/data/liveline_data.py
liveline/model/__init__.py
liveline/model/account.py
liveline/model/equity.py
liveline/model/order.py
liveline/model/portfolio.py
liveline/model/position.py
liveline/model/quote.py
liveline/order/__init__.py
liveline/order/liveline_order.py
liveline/order/order_executor.py
liveline/web/__init__.py
liveline/web/executions.py
liveline/web/overview.py
liveline/web/status.py
liveline/web/strategy.py
liveline-1.1.dist-info/METADATA
liveline-1.1.dist-info/RECORD
liveline-1.1.dist-info/WHEEL
liveline-1.1.dist-info/top_level.txt
