Metadata-Version: 2.1
Name: liveline
Version: 1.1
Summary: Python live trading framework
Home-page: UNKNOWN
Author: Daniel Wang
Author-email: danielwpz@gmail.com
License: MIT
Platform: UNKNOWN
Requires-Dist: arrow
Requires-Dist: maya
Requires-Dist: pandas
Requires-Dist: pymongo
Requires-Dist: pytz
Requires-Dist: schedule
Requires-Dist: flask
Requires-Dist: pandas-market-calendars
